crop_sensing/__init__.py
crop_sensing/cobot_manager.py
crop_sensing/create_plc.py
crop_sensing/find_plant.py
crop_sensing/main.py
crop_sensing/zed_manager.py
unimi_crop_sensing-1.1.dist-info/METADATA
unimi_crop_sensing-1.1.dist-info/WHEEL
unimi_crop_sensing-1.1.dist-info/top_level.txt
unimi_crop_sensing-1.1.dist-info/RECORD
