Metadata-Version: 2.4
Name: unimi_crop_sensing
Version: 1.1
Summary: A toolkit for crop sensing using the ZED camera
Home-page: https://github.com/Hoppip48/unimi_crop_sensing
Requires-Dist: opencv-python
Requires-Dist: pyzed==5.0
Requires-Dist: numpy
Requires-Dist: scikit-image
Requires-Dist: scikit-learn
Requires-Dist: websocket
Requires-Dist: os
Dynamic: description
Dynamic: description-content-type
Dynamic: home-page
Dynamic: requires-dist
Dynamic: summary
